root_finding/__init__.py
root_finding_pkg_thanjira-0.0.3.dist-info/METADATA
root_finding_pkg_thanjira-0.0.3.dist-info/WHEEL
root_finding_pkg_thanjira-0.0.3.dist-info/top_level.txt
root_finding_pkg_thanjira-0.0.3.dist-info/RECORD
