Metadata-Version: 2.1
Name: root-finding-pkg-thanjira
Version: 0.0.3
Summary: Root-Finding optimization
Home-page: UNKNOWN
Author: Thanjira Pornsasawat
Author-email: tp1u19@soton.ac.uk
License: MIT
Keywords: goldenSection,bisection,newton,secant,brent,quasi-newton,trust region
Platform: UNKNOWN
Classifier: Development Status :: 5 - Production/Stable
Classifier: Intended Audience :: Education
Classifier: Operating System :: Microsoft :: Windows :: Windows 10
Classifier: License :: OSI Approved :: MIT License
Classifier: Programming Language :: Python :: 3
